Workbook
Name aporte: Investimentos!$D$12
Name patrimonio: Investimentos!$D$15
Name qtd_anos: Investimentos!$D$13
Name rendimento_carteira: Investimentos!$D$8
Name salario: Investimentos!$D$7
Name sugestao_investimento: Investimentos!$D$9
Name taxa_mensal: Investimentos!$D$14

Sheet Investimentos
B4: Simulador de investimentos em FIIs
B6: CONFIGURAÇÕES
B7: Salário | D7: 2000
B8: Rendimento da carteira | D8: 0.006
B9: Sugestão de investimento | D9: =salario*30% -> 600
B11: INVESTIMENTO MENSAL
B12: Quanto investir por mês? | D12: 200
B13: Por quantos anos? | D13: 5
B14: Taxa de rendimento mensal | D14: 0.01079
B15: Patrimônio acumulado | D15: =FV(taxa_mensal,qtd_anos*12,-aporte) -> 16755.383
B16: Dividendos mensais | D16: =patrimonio*rendimento_carteira -> 100.5323
B19: CENÁRIOS
B20: Prazo em anos | C20: Patrimônio | D20: Dividendos mensais
B21: 2 | C21: =FV($D$14,B21*12,-$D$12) -> 5445.5255 | D21: =C21*$D$8 -> 32.673153
B22: 5 | C22: =FV($D$14,B22*12,-$D$12) -> 16755.383 | D22: =C22*$D$8 -> 100.5323
B23: 10 | C23: =FV($D$14,B23*12,-$D$12) -> 48656.843 | D23: =C23*$D$8 -> 291.94106
B24: 20 | C24: =FV($D$14,B24*12,-$D$12) -> 225039.68 | D24: =C24*$D$8 -> 1350.2381
B25: 30 | C25: =FV($D$14,B25*12,-$D$12) -> 864433.93 | D25: =C25*$D$8 -> 5186.6036
B28: PERFIL DO INVESTIDOR
B29: Perfil | D29: Moderado
B30: Valor investido por mês | D30: =aporte -> 200
B32: Tipo de FII | C32: Percentual sugerido | D32: Valor
B33: PAPEL | C33: =VLOOKUP($D$29&"-"&B33,'Tabela de apoio'!$B$4:$E$21,4,FALSE) -> 0.32 | D33: =C33*$D$30 -> 64
B34: TIJOLO | C34: =VLOOKUP($D$29&"-"&B34,'Tabela de apoio'!$B$4:$E$21,4,FALSE) -> 0.4 | D34: =C34*$D$30 -> 80
B35: HÍBRIDOS | C35: =VLOOKUP($D$29&"-"&B35,'Tabela de apoio'!$B$4:$E$21,4,FALSE) -> 0.08 | D35: =C35*$D$30 -> 16
B36: FOFs | C36: =VLOOKUP($D$29&"-"&B36,'Tabela de apoio'!$B$4:$E$21,4,FALSE) -> 0.1 | D36: =C36*$D$30 -> 20
B37: DESENVOLVIMENTO | C37: =VLOOKUP($D$29&"-"&B37,'Tabela de apoio'!$B$4:$E$21,4,FALSE) -> 0.05 | D37: =C37*$D$30 -> 10
B38: HOTELARIAS | C38: =VLOOKUP($D$29&"-"&B38,'Tabela de apoio'!$B$4:$E$21,4,FALSE) -> 0.05 | D38: =C38*$D$30 -> 10
B39: Total | C39: =ROUND(SUM(C33:C38),10) -> 1 | D39: =SUM(D33:D38) -> 200

Sheet Tabela de apoio
B2: Tabela de apoio
B3: Chave | C3: Perfil | D3: Tipo de FII | E3: Percentual
B4: =C4&"-"&D4 -> Conservador-PAPEL | C4: Conservador | D4: PAPEL | E4: 0.3
B5: =C5&"-"&D5 -> Conservador-TIJOLO | C5: Conservador | D5: TIJOLO | E5: 0.5
B6: =C6&"-"&D6 -> Conservador-HÍBRIDOS | C6: Conservador | D6: HÍBRIDOS | E6: 0.1
B7: =C7&"-"&D7 -> Conservador-FOFs | C7: Conservador | D7: FOFs | E7: 0.1
B8: =C8&"-"&D8 -> Conservador-DESENVOLVIMENTO | C8: Conservador | D8: DESENVOLVIMENTO | E8: 0
B9: =C9&"-"&D9 -> Conservador-HOTELARIAS | C9: Conservador | D9: HOTELARIAS | E9: 0
B10: =C10&"-"&D10 -> Moderado-PAPEL | C10: Moderado | D10: PAPEL | E10: 0.32
B11: =C11&"-"&D11 -> Moderado-TIJOLO | C11: Moderado | D11: TIJOLO | E11: 0.4
B12: =C12&"-"&D12 -> Moderado-HÍBRIDOS | C12: Moderado | D12: HÍBRIDOS | E12: 0.08
B13: =C13&"-"&D13 -> Moderado-FOFs | C13: Moderado | D13: FOFs | E13: 0.1
B14: =C14&"-"&D14 -> Moderado-DESENVOLVIMENTO | C14: Moderado | D14: DESENVOLVIMENTO | E14: 0.05
B15: =C15&"-"&D15 -> Moderado-HOTELARIAS | C15: Moderado | D15: HOTELARIAS | E15: 0.05
... B21: =C21&"-"&D21 -> Agressivo-HOTELARIAS | C21: Agressivo | D21: HOTELARIAS | E21: 0.1
